consul_lib/__init__.py
consul_lib/lock.py
consul_lib/semaphore.py
consul_lib/services.py
consul_lib/session.py
consul_lib-0.1.7.dev0.dist-info/LICENSE
consul_lib-0.1.7.dev0.dist-info/METADATA
consul_lib-0.1.7.dev0.dist-info/WHEEL
consul_lib-0.1.7.dev0.dist-info/top_level.txt
consul_lib-0.1.7.dev0.dist-info/RECORD
